{
  "surah_number": 77,
  "name_en": "Al-Mursalat",
  "name_ar": "المرسلات",
  "verses_count": 50,
  "revelation_place": "makkah",
  "verses": [
    {
      "global_id": 5623,
      "surah": 77,
      "ayah": 1,
      "verse_key": "77:1",
      "text_ar": " وَٱلْمُرْسَلَـٰتِ عُرْفًا",
      "text_en_pickthall": "By the emissary winds, (sent) one after another"
    },
    {
      "global_id": 5624,
      "surah": 77,
      "ayah": 2,
      "verse_key": "77:2",
      "text_ar": "فَٱلْعَـٰصِفَـٰتِ عَصْفًا",
      "text_en_pickthall": "By the raging hurricanes,"
    },
    {
      "global_id": 5625,
      "surah": 77,
      "ayah": 3,
      "verse_key": "77:3",
      "text_ar": "وَٱلنَّـٰشِرَٰتِ نَشْرًا",
      "text_en_pickthall": "By those which cause earth´s vegetation to revive;"
    },
    {
      "global_id": 5626,
      "surah": 77,
      "ayah": 4,
      "verse_key": "77:4",
      "text_ar": "فَٱلْفَـٰرِقَـٰتِ فَرْقًا",
      "text_en_pickthall": "By those who winnow with a winnowing,"
    },
    {
      "global_id": 5627,
      "surah": 77,
      "ayah": 5,
      "verse_key": "77:5",
      "text_ar": "فَٱلْمُلْقِيَـٰتِ ذِكْرًا",
      "text_en_pickthall": "By those who bring down the Reminder,"
    },
    {
      "global_id": 5628,
      "surah": 77,
      "ayah": 6,
      "verse_key": "77:6",
      "text_ar": "عُذْرًا أَوْ نُذْرًا",
      "text_en_pickthall": "To excuse or to warn,"
    },
    {
      "global_id": 5629,
      "surah": 77,
      "ayah": 7,
      "verse_key": "77:7",
      "text_ar": "إِنَّمَا تُوعَدُونَ لَوَٰقِعٌ",
      "text_en_pickthall": "Surely that which ye are promised will befall."
    },
    {
      "global_id": 5630,
      "surah": 77,
      "ayah": 8,
      "verse_key": "77:8",
      "text_ar": "فَإِذَا ٱلنُّجُومُ طُمِسَتْ",
      "text_en_pickthall": "So when the stars are put out,"
    },
    {
      "global_id": 5631,
      "surah": 77,
      "ayah": 9,
      "verse_key": "77:9",
      "text_ar": "وَإِذَا ٱلسَّمَآءُ فُرِجَتْ",
      "text_en_pickthall": "And when the sky is riven asunder,"
    },
    {
      "global_id": 5632,
      "surah": 77,
      "ayah": 10,
      "verse_key": "77:10",
      "text_ar": "وَإِذَا ٱلْجِبَالُ نُسِفَتْ",
      "text_en_pickthall": "And when the mountains are blown away,"
    },
    {
      "global_id": 5633,
      "surah": 77,
      "ayah": 11,
      "verse_key": "77:11",
      "text_ar": "وَإِذَا ٱلرُّسُلُ أُقِّتَتْ",
      "text_en_pickthall": "And when the messengers are brought unto their time appointed -"
    },
    {
      "global_id": 5634,
      "surah": 77,
      "ayah": 12,
      "verse_key": "77:12",
      "text_ar": "لِأَىِّ يَوْمٍ أُجِّلَتْ",
      "text_en_pickthall": "For what day is the time appointed?"
    },
    {
      "global_id": 5635,
      "surah": 77,
      "ayah": 13,
      "verse_key": "77:13",
      "text_ar": "لِيَوْمِ ٱلْفَصْلِ",
      "text_en_pickthall": "For the Day of Decision."
    },
    {
      "global_id": 5636,
      "surah": 77,
      "ayah": 14,
      "verse_key": "77:14",
      "text_ar": "وَمَآ أَدْرَىٰكَ مَا يَوْمُ ٱلْفَصْلِ",
      "text_en_pickthall": "And what will convey unto thee what the Day of Decision is! -"
    },
    {
      "global_id": 5637,
      "surah": 77,
      "ayah": 15,
      "verse_key": "77:15",
      "text_ar": "وَيْلٌ يَوْمَئِذٍ لِّلْمُكَذِّبِينَ",
      "text_en_pickthall": "Woe unto the repudiators on that day!"
    },
    {
      "global_id": 5638,
      "surah": 77,
      "ayah": 16,
      "verse_key": "77:16",
      "text_ar": "أَلَمْ نُهْلِكِ ٱلْأَوَّلِينَ",
      "text_en_pickthall": "Destroyed We not the former folk,"
    },
    {
      "global_id": 5639,
      "surah": 77,
      "ayah": 17,
      "verse_key": "77:17",
      "text_ar": "ثُمَّ نُتْبِعُهُمُ ٱلْـَٔاخِرِينَ",
      "text_en_pickthall": "Then caused the latter folk to follow after?"
    },
    {
      "global_id": 5640,
      "surah": 77,
      "ayah": 18,
      "verse_key": "77:18",
      "text_ar": "كَذَٰلِكَ نَفْعَلُ بِٱلْمُجْرِمِينَ",
      "text_en_pickthall": "Thus deal We ever with the guilty."
    },
    {
      "global_id": 5641,
      "surah": 77,
      "ayah": 19,
      "verse_key": "77:19",
      "text_ar": "وَيْلٌ يَوْمَئِذٍ لِّلْمُكَذِّبِينَ",
      "text_en_pickthall": "Woe unto the repudiators on that day!"
    },
    {
      "global_id": 5642,
      "surah": 77,
      "ayah": 20,
      "verse_key": "77:20",
      "text_ar": "أَلَمْ نَخْلُقكُّم مِّن مَّآءٍ مَّهِينٍ",
      "text_en_pickthall": "Did We not create you from a base fluid"
    },
    {
      "global_id": 5643,
      "surah": 77,
      "ayah": 21,
      "verse_key": "77:21",
      "text_ar": "فَجَعَلْنَـٰهُ فِى قَرَارٍ مَّكِينٍ",
      "text_en_pickthall": "Which We laid up in a safe abode"
    },
    {
      "global_id": 5644,
      "surah": 77,
      "ayah": 22,
      "verse_key": "77:22",
      "text_ar": "إِلَىٰ قَدَرٍ مَّعْلُومٍ",
      "text_en_pickthall": "For a known term?"
    },
    {
      "global_id": 5645,
      "surah": 77,
      "ayah": 23,
      "verse_key": "77:23",
      "text_ar": "فَقَدَرْنَا فَنِعْمَ ٱلْقَـٰدِرُونَ",
      "text_en_pickthall": "Thus We arranged. How excellent is Our arranging!"
    },
    {
      "global_id": 5646,
      "surah": 77,
      "ayah": 24,
      "verse_key": "77:24",
      "text_ar": "وَيْلٌ يَوْمَئِذٍ لِّلْمُكَذِّبِينَ",
      "text_en_pickthall": "Woe unto the repudiators on that day!"
    },
    {
      "global_id": 5647,
      "surah": 77,
      "ayah": 25,
      "verse_key": "77:25",
      "text_ar": "أَلَمْ نَجْعَلِ ٱلْأَرْضَ كِفَاتًا",
      "text_en_pickthall": "Have We not made the earth a receptacle"
    },
    {
      "global_id": 5648,
      "surah": 77,
      "ayah": 26,
      "verse_key": "77:26",
      "text_ar": "أَحْيَآءً وَأَمْوَٰتًا",
      "text_en_pickthall": "Both for the living and the dead,"
    },
    {
      "global_id": 5649,
      "surah": 77,
      "ayah": 27,
      "verse_key": "77:27",
      "text_ar": "وَجَعَلْنَا فِيهَا رَوَٰسِىَ شَـٰمِخَـٰتٍ وَأَسْقَيْنَـٰكُم مَّآءً فُرَاتًا",
      "text_en_pickthall": "And placed therein high mountains and given you to drink sweet water therein?"
    },
    {
      "global_id": 5650,
      "surah": 77,
      "ayah": 28,
      "verse_key": "77:28",
      "text_ar": "وَيْلٌ يَوْمَئِذٍ لِّلْمُكَذِّبِينَ",
      "text_en_pickthall": "Woe unto the repudiators on that day!"
    },
    {
      "global_id": 5651,
      "surah": 77,
      "ayah": 29,
      "verse_key": "77:29",
      "text_ar": "ٱنطَلِقُوٓا۟ إِلَىٰ مَا كُنتُم بِهِۦ تُكَذِّبُونَ",
      "text_en_pickthall": "(It will be said unto them:) Depart unto that (doom) which ye used to deny;"
    },
    {
      "global_id": 5652,
      "surah": 77,
      "ayah": 30,
      "verse_key": "77:30",
      "text_ar": "ٱنطَلِقُوٓا۟ إِلَىٰ ظِلٍّ ذِى ثَلَـٰثِ شُعَبٍ",
      "text_en_pickthall": "Depart unto the shadow falling threefold,"
    },
    {
      "global_id": 5653,
      "surah": 77,
      "ayah": 31,
      "verse_key": "77:31",
      "text_ar": "لَّا ظَلِيلٍ وَلَا يُغْنِى مِنَ ٱللَّهَبِ",
      "text_en_pickthall": "(Which yet is) no relief nor shelter from the flame."
    },
    {
      "global_id": 5654,
      "surah": 77,
      "ayah": 32,
      "verse_key": "77:32",
      "text_ar": "إِنَّهَا تَرْمِى بِشَرَرٍ كَٱلْقَصْرِ",
      "text_en_pickthall": "Lo! it throweth up sparks like the castles,"
    },
    {
      "global_id": 5655,
      "surah": 77,
      "ayah": 33,
      "verse_key": "77:33",
      "text_ar": "كَأَنَّهُۥ جِمَـٰلَتٌ صُفْرٌ",
      "text_en_pickthall": "(Or) as it might be camels of bright yellow hue."
    },
    {
      "global_id": 5656,
      "surah": 77,
      "ayah": 34,
      "verse_key": "77:34",
      "text_ar": "وَيْلٌ يَوْمَئِذٍ لِّلْمُكَذِّبِينَ",
      "text_en_pickthall": "Woe unto the repudiators on that day!"
    },
    {
      "global_id": 5657,
      "surah": 77,
      "ayah": 35,
      "verse_key": "77:35",
      "text_ar": "هَـٰذَا يَوْمُ لَا يَنطِقُونَ",
      "text_en_pickthall": "This is a day wherein they speak not,"
    },
    {
      "global_id": 5658,
      "surah": 77,
      "ayah": 36,
      "verse_key": "77:36",
      "text_ar": "وَلَا يُؤْذَنُ لَهُمْ فَيَعْتَذِرُونَ",
      "text_en_pickthall": "Nor are they suffered to put forth excuses."
    },
    {
      "global_id": 5659,
      "surah": 77,
      "ayah": 37,
      "verse_key": "77:37",
      "text_ar": "وَيْلٌ يَوْمَئِذٍ لِّلْمُكَذِّبِينَ",
      "text_en_pickthall": "Woe unto the repudiators on that day!"
    },
    {
      "global_id": 5660,
      "surah": 77,
      "ayah": 38,
      "verse_key": "77:38",
      "text_ar": "هَـٰذَا يَوْمُ ٱلْفَصْلِ ۖ جَمَعْنَـٰكُمْ وَٱلْأَوَّلِينَ",
      "text_en_pickthall": "This is the Day of Decision, We have brought you and the men of old together."
    },
    {
      "global_id": 5661,
      "surah": 77,
      "ayah": 39,
      "verse_key": "77:39",
      "text_ar": "فَإِن كَانَ لَكُمْ كَيْدٌ فَكِيدُونِ",
      "text_en_pickthall": "If now ye have any wit, outwit Me."
    },
    {
      "global_id": 5662,
      "surah": 77,
      "ayah": 40,
      "verse_key": "77:40",
      "text_ar": "وَيْلٌ يَوْمَئِذٍ لِّلْمُكَذِّبِينَ",
      "text_en_pickthall": "Woe unto the repudiators on that day!"
    },
    {
      "global_id": 5663,
      "surah": 77,
      "ayah": 41,
      "verse_key": "77:41",
      "text_ar": "إِنَّ ٱلْمُتَّقِينَ فِى ظِلَـٰلٍ وَعُيُونٍ",
      "text_en_pickthall": "Lo! those who kept their duty are amid shade and fountains,"
    },
    {
      "global_id": 5664,
      "surah": 77,
      "ayah": 42,
      "verse_key": "77:42",
      "text_ar": "وَفَوَٰكِهَ مِمَّا يَشْتَهُونَ",
      "text_en_pickthall": "And fruits such as they desire."
    },
    {
      "global_id": 5665,
      "surah": 77,
      "ayah": 43,
      "verse_key": "77:43",
      "text_ar": "كُلُوا۟ وَٱشْرَبُوا۟ هَنِيٓـًٔۢا بِمَا كُنتُمْ تَعْمَلُونَ",
      "text_en_pickthall": "(Unto them it is said:) Eat, drink and welcome, O ye blessed, in return for what ye did."
    },
    {
      "global_id": 5666,
      "surah": 77,
      "ayah": 44,
      "verse_key": "77:44",
      "text_ar": "إِنَّا كَذَٰلِكَ نَجْزِى ٱلْمُحْسِنِينَ",
      "text_en_pickthall": "Thus do We reward the good."
    },
    {
      "global_id": 5667,
      "surah": 77,
      "ayah": 45,
      "verse_key": "77:45",
      "text_ar": "وَيْلٌ يَوْمَئِذٍ لِّلْمُكَذِّبِينَ",
      "text_en_pickthall": "Woe unto the repudiators on that day!"
    },
    {
      "global_id": 5668,
      "surah": 77,
      "ayah": 46,
      "verse_key": "77:46",
      "text_ar": "كُلُوا۟ وَتَمَتَّعُوا۟ قَلِيلًا إِنَّكُم مُّجْرِمُونَ",
      "text_en_pickthall": "Eat and take your ease (on earth) a little. Lo! ye are guilty."
    },
    {
      "global_id": 5669,
      "surah": 77,
      "ayah": 47,
      "verse_key": "77:47",
      "text_ar": "وَيْلٌ يَوْمَئِذٍ لِّلْمُكَذِّبِينَ",
      "text_en_pickthall": "Woe unto the repudiators on that day!"
    },
    {
      "global_id": 5670,
      "surah": 77,
      "ayah": 48,
      "verse_key": "77:48",
      "text_ar": "وَإِذَا قِيلَ لَهُمُ ٱرْكَعُوا۟ لَا يَرْكَعُونَ",
      "text_en_pickthall": "When it is said unto them: Bow down, they bow not down!"
    },
    {
      "global_id": 5671,
      "surah": 77,
      "ayah": 49,
      "verse_key": "77:49",
      "text_ar": "وَيْلٌ يَوْمَئِذٍ لِّلْمُكَذِّبِينَ",
      "text_en_pickthall": "Woe unto the repudiators on that day!"
    },
    {
      "global_id": 5672,
      "surah": 77,
      "ayah": 50,
      "verse_key": "77:50",
      "text_ar": "فَبِأَىِّ حَدِيثٍۭ بَعْدَهُۥ يُؤْمِنُونَ",
      "text_en_pickthall": "In what statement, after this, will they believe?"
    }
  ]
}
